spPersist/DTM_filtrations.py
spPersist/__init__.py
spPersist/dp.py
spPersist/hc.py
spPersist/persistence_statistics.py
spPersist/ph.py
spPersist/pp.py
sppersist-1.2.4.dist-info/METADATA
sppersist-1.2.4.dist-info/WHEEL
sppersist-1.2.4.dist-info/licenses/LICENSE
sppersist-1.2.4.dist-info/RECORD
