Metadata-Version: 2.1
Name: spPersist
Version: 1.2.4
Summary: Spatial transcriptomics with Persistent Homology
Author-email: Lirong Yang <lirong.yang@outlook.com>
License-File: LICENSE
Classifier: License :: OSI Approved :: MIT License
Classifier: Operating System :: OS Independent
Classifier: Programming Language :: Python :: 3
Requires-Python: >=3.7
Requires-Dist: cell2location
Requires-Dist: gcsfs
Requires-Dist: gudhi
Requires-Dist: leidenalg
Requires-Dist: scanpy
